Metadata-Version: 2.1
Name: Myplayer
Version: 1.3.0
Summary: Um reprodutor de músicas em python!
Author: Eduardo Martins Panassi
Author-email: edumartinpanassi@gmail.com
